flora_cam/__init__.py
flora_cam/flora_cam.py
flutter/flora_cam/pubspec.yaml
flutter/flora_cam/lib/flora_cam.dart
flutter/flora_cam/lib/src/create_control.dart
flutter/flora_cam/lib/src/flora_cam.dart
flora_cam-1.0.0.dist-info/METADATA
flora_cam-1.0.0.dist-info/WHEEL
flora_cam-1.0.0.dist-info/top_level.txt
flora_cam-1.0.0.dist-info/RECORD
